<?xml version="1.0" encoding="UTF-8"?>
<!--
	TurtleExample1 application - Inheritance Hierarchy
	Author: KenWebb
	Date:   21/02/2007
	File:   TurtleExample1.mdzip
	Target: Xholon 0.5 http://www.primordion.com/Xholon
	UML: MagicDraw UML 11.5
	XMI: 2.1, Wed Feb 21 13:46:13 EST 2007
	XSLT: 1, Apache Software Foundation, http://xml.apache.org/xalan-j
-->
<XholonClass xmlns:xi="http://www.w3.org/2001/XInclude"
	xmlns:xmi="http://schema.omg.org/spec/XMI/2.1"
	xmlns:uml="http://schema.omg.org/spec/UML/2.0">
	<TheSystem/>
	<TurtleObserver/>
	<PatchOwner/>
	<Row/>
	<Patch/>
	<Turtle>
		<Sheep/>
		<Wolf/>
	</Turtle>
	<!-- StateMachineEntity -->
	<!--<xi:include href="_mechanism/StateMachineEntity.xml"/>-->
	<!-- Port -->
	<!--<xi:include href="_mechanism/Port.xml"/>-->
	<!-- Xholon Viewers -->
	<!--<xi:include href="_viewer/XholonViewer.xml"/>-->
</XholonClass>
